{
  "id": 609,
  "name": "chandelure",
  "image": "https://raw.githubusercontent.com/PokeAPI/sprites/master/sprites/pokemon/other/official-artwork/609.png",
  "imageShiny": "https://raw.githubusercontent.com/PokeAPI/sprites/master/sprites/pokemon/other/official-artwork/shiny/609.png",
  "types": [
    "ghost",
    "fire"
  ],
  "height": 1,
  "weight": 34.3,
  "stats": {
    "hp": 60,
    "attack": 55,
    "defense": 90,
    "specialAttack": 145,
    "specialDefense": 90,
    "speed": 80,
    "total": 520
  },
  "abilities": [
    {
      "name": "flash-fire",
      "isHidden": false
    },
    {
      "name": "flame-body",
      "isHidden": false
    },
    {
      "name": "infiltrator",
      "isHidden": true
    }
  ],
  "typeEffectiveness": {
    "weaknesses": [
      "dark",
      "ghost",
      "ground",
      "rock",
      "water"
    ],
    "resistances": [
      "bug",
      "fairy",
      "fire",
      "grass",
      "ice",
      "poison",
      "steel"
    ],
    "immunities": [
      "fighting",
      "normal"
    ]
  },
  "evolutionChain": [
    {
      "name": "litwick",
      "id": 607
    },
    {
      "name": "lampent",
      "id": 608
    },
    {
      "name": "chandelure",
      "id": 609
    }
  ],
  "locations": {},
  "movesByLevel": {
    "gen-sword-shield": [
      {
        "name": "ember",
        "level": 1,
        "url": "https://pokeapi.co/api/v2/move/52/"
      },
      {
        "name": "fire-spin",
        "level": 1,
        "url": "https://pokeapi.co/api/v2/move/83/"
      },
      {
        "name": "night-shade",
        "level": 1,
        "url": "https://pokeapi.co/api/v2/move/101/"
      },
      {
        "name": "minimize",
        "level": 1,
        "url": "https://pokeapi.co/api/v2/move/107/"
      },
      {
        "name": "confuse-ray",
        "level": 1,
        "url": "https://pokeapi.co/api/v2/move/109/"
      },
      {
        "name": "smog",
        "level": 1,
        "url": "https://pokeapi.co/api/v2/move/123/"
      },
      {
        "name": "curse",
        "level": 1,
        "url": "https://pokeapi.co/api/v2/move/174/"
      },
      {
        "name": "pain-split",
        "level": 1,
        "url": "https://pokeapi.co/api/v2/move/220/"
      },
      {
        "name": "shadow-ball",
        "level": 1,
        "url": "https://pokeapi.co/api/v2/move/247/"
      },
      {
        "name": "will-o-wisp",
        "level": 1,
        "url": "https://pokeapi.co/api/v2/move/261/"
      },
      {
        "name": "memento",
        "level": 1,
        "url": "https://pokeapi.co/api/v2/move/262/"
      },
      {
        "name": "imprison",
        "level": 1,
        "url": "https://pokeapi.co/api/v2/move/286/"
      },
      {
        "name": "astonish",
        "level": 1,
        "url": "https://pokeapi.co/api/v2/move/310/"
      },
      {
        "name": "overheat",
        "level": 1,
        "url": "https://pokeapi.co/api/v2/move/315/"
      },
      {
        "name": "hex",
        "level": 1,
        "url": "https://pokeapi.co/api/v2/move/506/"
      },
      {
        "name": "inferno",
        "level": 1,
        "url": "https://pokeapi.co/api/v2/move/517/"
      }
    ],
    "gen-scarlet-violet": [
      {
        "name": "ember",
        "level": 1,
        "url": "https://pokeapi.co/api/v2/move/52/"
      },
      {
        "name": "fire-spin",
        "level": 1,
        "url": "https://pokeapi.co/api/v2/move/83/"
      },
      {
        "name": "night-shade",
        "level": 1,
        "url": "https://pokeapi.co/api/v2/move/101/"
      },
      {
        "name": "minimize",
        "level": 1,
        "url": "https://pokeapi.co/api/v2/move/107/"
      },
      {
        "name": "confuse-ray",
        "level": 1,
        "url": "https://pokeapi.co/api/v2/move/109/"
      },
      {
        "name": "smog",
        "level": 1,
        "url": "https://pokeapi.co/api/v2/move/123/"
      },
      {
        "name": "curse",
        "level": 1,
        "url": "https://pokeapi.co/api/v2/move/174/"
      },
      {
        "name": "pain-split",
        "level": 1,
        "url": "https://pokeapi.co/api/v2/move/220/"
      },
      {
        "name": "shadow-ball",
        "level": 1,
        "url": "https://pokeapi.co/api/v2/move/247/"
      },
      {
        "name": "will-o-wisp",
        "level": 1,
        "url": "https://pokeapi.co/api/v2/move/261/"
      },
      {
        "name": "memento",
        "level": 1,
        "url": "https://pokeapi.co/api/v2/move/262/"
      },
      {
        "name": "imprison",
        "level": 1,
        "url": "https://pokeapi.co/api/v2/move/286/"
      },
      {
        "name": "astonish",
        "level": 1,
        "url": "https://pokeapi.co/api/v2/move/310/"
      },
      {
        "name": "overheat",
        "level": 1,
        "url": "https://pokeapi.co/api/v2/move/315/"
      },
      {
        "name": "hex",
        "level": 1,
        "url": "https://pokeapi.co/api/v2/move/506/"
      },
      {
        "name": "inferno",
        "level": 1,
        "url": "https://pokeapi.co/api/v2/move/517/"
      }
    ],
    "gen-black-white": [
      {
        "name": "confuse-ray",
        "level": 1,
        "url": "https://pokeapi.co/api/v2/move/109/"
      },
      {
        "name": "smog",
        "level": 1,
        "url": "https://pokeapi.co/api/v2/move/123/"
      },
      {
        "name": "flame-burst",
        "level": 1,
        "url": "https://pokeapi.co/api/v2/move/481/"
      },
      {
        "name": "hex",
        "level": 1,
        "url": "https://pokeapi.co/api/v2/move/506/"
      }
    ],
    "gen-black-2-white-2": [
      {
        "name": "confuse-ray",
        "level": 1,
        "url": "https://pokeapi.co/api/v2/move/109/"
      },
      {
        "name": "smog",
        "level": 1,
        "url": "https://pokeapi.co/api/v2/move/123/"
      },
      {
        "name": "flame-burst",
        "level": 1,
        "url": "https://pokeapi.co/api/v2/move/481/"
      },
      {
        "name": "hex",
        "level": 1,
        "url": "https://pokeapi.co/api/v2/move/506/"
      }
    ],
    "gen-x-y": [
      {
        "name": "confuse-ray",
        "level": 1,
        "url": "https://pokeapi.co/api/v2/move/109/"
      },
      {
        "name": "smog",
        "level": 1,
        "url": "https://pokeapi.co/api/v2/move/123/"
      },
      {
        "name": "pain-split",
        "level": 1,
        "url": "https://pokeapi.co/api/v2/move/220/"
      },
      {
        "name": "flame-burst",
        "level": 1,
        "url": "https://pokeapi.co/api/v2/move/481/"
      },
      {
        "name": "hex",
        "level": 1,
        "url": "https://pokeapi.co/api/v2/move/506/"
      }
    ],
    "gen-omega-ruby-alpha-sapphire": [
      {
        "name": "confuse-ray",
        "level": 1,
        "url": "https://pokeapi.co/api/v2/move/109/"
      },
      {
        "name": "smog",
        "level": 1,
        "url": "https://pokeapi.co/api/v2/move/123/"
      },
      {
        "name": "pain-split",
        "level": 1,
        "url": "https://pokeapi.co/api/v2/move/220/"
      },
      {
        "name": "flame-burst",
        "level": 1,
        "url": "https://pokeapi.co/api/v2/move/481/"
      },
      {
        "name": "hex",
        "level": 1,
        "url": "https://pokeapi.co/api/v2/move/506/"
      }
    ],
    "gen-sun-moon": [
      {
        "name": "confuse-ray",
        "level": 1,
        "url": "https://pokeapi.co/api/v2/move/109/"
      },
      {
        "name": "smog",
        "level": 1,
        "url": "https://pokeapi.co/api/v2/move/123/"
      },
      {
        "name": "pain-split",
        "level": 1,
        "url": "https://pokeapi.co/api/v2/move/220/"
      },
      {
        "name": "flame-burst",
        "level": 1,
        "url": "https://pokeapi.co/api/v2/move/481/"
      },
      {
        "name": "hex",
        "level": 1,
        "url": "https://pokeapi.co/api/v2/move/506/"
      }
    ],
    "gen-ultra-sun-ultra-moon": [
      {
        "name": "confuse-ray",
        "level": 1,
        "url": "https://pokeapi.co/api/v2/move/109/"
      },
      {
        "name": "smog",
        "level": 1,
        "url": "https://pokeapi.co/api/v2/move/123/"
      },
      {
        "name": "pain-split",
        "level": 1,
        "url": "https://pokeapi.co/api/v2/move/220/"
      },
      {
        "name": "flame-burst",
        "level": 1,
        "url": "https://pokeapi.co/api/v2/move/481/"
      },
      {
        "name": "hex",
        "level": 1,
        "url": "https://pokeapi.co/api/v2/move/506/"
      }
    ]
  },
  "movesByMachine": {
    "gen-black-white": [
      {
        "name": "flamethrower",
        "url": "https://pokeapi.co/api/v2/move/53/"
      },
      {
        "name": "hyper-beam",
        "url": "https://pokeapi.co/api/v2/move/63/"
      },
      {
        "name": "solar-beam",
        "url": "https://pokeapi.co/api/v2/move/76/"
      },
      {
        "name": "toxic",
        "url": "https://pokeapi.co/api/v2/move/92/"
      },
      {
        "name": "psychic",
        "url": "https://pokeapi.co/api/v2/move/94/"
      },
      {
        "name": "double-team",
        "url": "https://pokeapi.co/api/v2/move/104/"
      },
      {
        "name": "fire-blast",
        "url": "https://pokeapi.co/api/v2/move/126/"
      },
      {
        "name": "dream-eater",
        "url": "https://pokeapi.co/api/v2/move/138/"
      },
      {
        "name": "flash",
        "url": "https://pokeapi.co/api/v2/move/148/"
      },
      {
        "name": "rest",
        "url": "https://pokeapi.co/api/v2/move/156/"
      },
      {
        "name": "substitute",
        "url": "https://pokeapi.co/api/v2/move/164/"
      },
      {
        "name": "thief",
        "url": "https://pokeapi.co/api/v2/move/168/"
      },
      {
        "name": "protect",
        "url": "https://pokeapi.co/api/v2/move/182/"
      },
      {
        "name": "swagger",
        "url": "https://pokeapi.co/api/v2/move/207/"
      },
      {
        "name": "attract",
        "url": "https://pokeapi.co/api/v2/move/213/"
      },
      {
        "name": "return",
        "url": "https://pokeapi.co/api/v2/move/216/"
      },
      {
        "name": "frustration",
        "url": "https://pokeapi.co/api/v2/move/218/"
      },
      {
        "name": "safeguard",
        "url": "https://pokeapi.co/api/v2/move/219/"
      },
      {
        "name": "hidden-power",
        "url": "https://pokeapi.co/api/v2/move/237/"
      },
      {
        "name": "sunny-day",
        "url": "https://pokeapi.co/api/v2/move/241/"
      },
      {
        "name": "psych-up",
        "url": "https://pokeapi.co/api/v2/move/244/"
      },
      {
        "name": "shadow-ball",
        "url": "https://pokeapi.co/api/v2/move/247/"
      },
      {
        "name": "will-o-wisp",
        "url": "https://pokeapi.co/api/v2/move/261/"
      },
      {
        "name": "facade",
        "url": "https://pokeapi.co/api/v2/move/263/"
      },
      {
        "name": "taunt",
        "url": "https://pokeapi.co/api/v2/move/269/"
      },
      {
        "name": "overheat",
        "url": "https://pokeapi.co/api/v2/move/315/"
      },
      {
        "name": "calm-mind",
        "url": "https://pokeapi.co/api/v2/move/347/"
      },
      {
        "name": "payback",
        "url": "https://pokeapi.co/api/v2/move/371/"
      },
      {
        "name": "embargo",
        "url": "https://pokeapi.co/api/v2/move/373/"
      },
      {
        "name": "energy-ball",
        "url": "https://pokeapi.co/api/v2/move/412/"
      },
      {
        "name": "giga-impact",
        "url": "https://pokeapi.co/api/v2/move/416/"
      },
      {
        "name": "trick-room",
        "url": "https://pokeapi.co/api/v2/move/433/"
      },
      {
        "name": "telekinesis",
        "url": "https://pokeapi.co/api/v2/move/477/"
      },
      {
        "name": "flame-charge",
        "url": "https://pokeapi.co/api/v2/move/488/"
      },
      {
        "name": "round",
        "url": "https://pokeapi.co/api/v2/move/496/"
      },
      {
        "name": "incinerate",
        "url": "https://pokeapi.co/api/v2/move/510/"
      }
    ],
    "gen-black-2-white-2": [
      {
        "name": "flamethrower",
        "url": "https://pokeapi.co/api/v2/move/53/"
      },
      {
        "name": "hyper-beam",
        "url": "https://pokeapi.co/api/v2/move/63/"
      },
      {
        "name": "solar-beam",
        "url": "https://pokeapi.co/api/v2/move/76/"
      },
      {
        "name": "toxic",
        "url": "https://pokeapi.co/api/v2/move/92/"
      },
      {
        "name": "psychic",
        "url": "https://pokeapi.co/api/v2/move/94/"
      },
      {
        "name": "double-team",
        "url": "https://pokeapi.co/api/v2/move/104/"
      },
      {
        "name": "fire-blast",
        "url": "https://pokeapi.co/api/v2/move/126/"
      },
      {
        "name": "dream-eater",
        "url": "https://pokeapi.co/api/v2/move/138/"
      },
      {
        "name": "flash",
        "url": "https://pokeapi.co/api/v2/move/148/"
      },
      {
        "name": "rest",
        "url": "https://pokeapi.co/api/v2/move/156/"
      },
      {
        "name": "substitute",
        "url": "https://pokeapi.co/api/v2/move/164/"
      },
      {
        "name": "thief",
        "url": "https://pokeapi.co/api/v2/move/168/"
      },
      {
        "name": "protect",
        "url": "https://pokeapi.co/api/v2/move/182/"
      },
      {
        "name": "swagger",
        "url": "https://pokeapi.co/api/v2/move/207/"
      },
      {
        "name": "attract",
        "url": "https://pokeapi.co/api/v2/move/213/"
      },
      {
        "name": "return",
        "url": "https://pokeapi.co/api/v2/move/216/"
      },
      {
        "name": "frustration",
        "url": "https://pokeapi.co/api/v2/move/218/"
      },
      {
        "name": "safeguard",
        "url": "https://pokeapi.co/api/v2/move/219/"
      },
      {
        "name": "hidden-power",
        "url": "https://pokeapi.co/api/v2/move/237/"
      },
      {
        "name": "sunny-day",
        "url": "https://pokeapi.co/api/v2/move/241/"
      },
      {
        "name": "psych-up",
        "url": "https://pokeapi.co/api/v2/move/244/"
      },
      {
        "name": "shadow-ball",
        "url": "https://pokeapi.co/api/v2/move/247/"
      },
      {
        "name": "will-o-wisp",
        "url": "https://pokeapi.co/api/v2/move/261/"
      },
      {
        "name": "facade",
        "url": "https://pokeapi.co/api/v2/move/263/"
      },
      {
        "name": "taunt",
        "url": "https://pokeapi.co/api/v2/move/269/"
      },
      {
        "name": "overheat",
        "url": "https://pokeapi.co/api/v2/move/315/"
      },
      {
        "name": "calm-mind",
        "url": "https://pokeapi.co/api/v2/move/347/"
      },
      {
        "name": "payback",
        "url": "https://pokeapi.co/api/v2/move/371/"
      },
      {
        "name": "embargo",
        "url": "https://pokeapi.co/api/v2/move/373/"
      },
      {
        "name": "energy-ball",
        "url": "https://pokeapi.co/api/v2/move/412/"
      },
      {
        "name": "giga-impact",
        "url": "https://pokeapi.co/api/v2/move/416/"
      },
      {
        "name": "trick-room",
        "url": "https://pokeapi.co/api/v2/move/433/"
      },
      {
        "name": "telekinesis",
        "url": "https://pokeapi.co/api/v2/move/477/"
      },
      {
        "name": "flame-charge",
        "url": "https://pokeapi.co/api/v2/move/488/"
      },
      {
        "name": "round",
        "url": "https://pokeapi.co/api/v2/move/496/"
      },
      {
        "name": "incinerate",
        "url": "https://pokeapi.co/api/v2/move/510/"
      }
    ],
    "gen-x-y": [
      {
        "name": "flamethrower",
        "url": "https://pokeapi.co/api/v2/move/53/"
      },
      {
        "name": "hyper-beam",
        "url": "https://pokeapi.co/api/v2/move/63/"
      },
      {
        "name": "solar-beam",
        "url": "https://pokeapi.co/api/v2/move/76/"
      },
      {
        "name": "toxic",
        "url": "https://pokeapi.co/api/v2/move/92/"
      },
      {
        "name": "psychic",
        "url": "https://pokeapi.co/api/v2/move/94/"
      },
      {
        "name": "double-team",
        "url": "https://pokeapi.co/api/v2/move/104/"
      },
      {
        "name": "fire-blast",
        "url": "https://pokeapi.co/api/v2/move/126/"
      },
      {
        "name": "dream-eater",
        "url": "https://pokeapi.co/api/v2/move/138/"
      },
      {
        "name": "flash",
        "url": "https://pokeapi.co/api/v2/move/148/"
      },
      {
        "name": "rest",
        "url": "https://pokeapi.co/api/v2/move/156/"
      },
      {
        "name": "substitute",
        "url": "https://pokeapi.co/api/v2/move/164/"
      },
      {
        "name": "thief",
        "url": "https://pokeapi.co/api/v2/move/168/"
      },
      {
        "name": "protect",
        "url": "https://pokeapi.co/api/v2/move/182/"
      },
      {
        "name": "swagger",
        "url": "https://pokeapi.co/api/v2/move/207/"
      },
      {
        "name": "attract",
        "url": "https://pokeapi.co/api/v2/move/213/"
      },
      {
        "name": "sleep-talk",
        "url": "https://pokeapi.co/api/v2/move/214/"
      },
      {
        "name": "return",
        "url": "https://pokeapi.co/api/v2/move/216/"
      },
      {
        "name": "frustration",
        "url": "https://pokeapi.co/api/v2/move/218/"
      },
      {
        "name": "safeguard",
        "url": "https://pokeapi.co/api/v2/move/219/"
      },
      {
        "name": "hidden-power",
        "url": "https://pokeapi.co/api/v2/move/237/"
      },
      {
        "name": "sunny-day",
        "url": "https://pokeapi.co/api/v2/move/241/"
      },
      {
        "name": "psych-up",
        "url": "https://pokeapi.co/api/v2/move/244/"
      },
      {
        "name": "shadow-ball",
        "url": "https://pokeapi.co/api/v2/move/247/"
      },
      {
        "name": "will-o-wisp",
        "url": "https://pokeapi.co/api/v2/move/261/"
      },
      {
        "name": "facade",
        "url": "https://pokeapi.co/api/v2/move/263/"
      },
      {
        "name": "taunt",
        "url": "https://pokeapi.co/api/v2/move/269/"
      },
      {
        "name": "overheat",
        "url": "https://pokeapi.co/api/v2/move/315/"
      },
      {
        "name": "calm-mind",
        "url": "https://pokeapi.co/api/v2/move/347/"
      },
      {
        "name": "payback",
        "url": "https://pokeapi.co/api/v2/move/371/"
      },
      {
        "name": "embargo",
        "url": "https://pokeapi.co/api/v2/move/373/"
      },
      {
        "name": "dark-pulse",
        "url": "https://pokeapi.co/api/v2/move/399/"
      },
      {
        "name": "energy-ball",
        "url": "https://pokeapi.co/api/v2/move/412/"
      },
      {
        "name": "giga-impact",
        "url": "https://pokeapi.co/api/v2/move/416/"
      },
      {
        "name": "trick-room",
        "url": "https://pokeapi.co/api/v2/move/433/"
      },
      {
        "name": "flame-charge",
        "url": "https://pokeapi.co/api/v2/move/488/"
      },
      {
        "name": "round",
        "url": "https://pokeapi.co/api/v2/move/496/"
      },
      {
        "name": "incinerate",
        "url": "https://pokeapi.co/api/v2/move/510/"
      },
      {
        "name": "confide",
        "url": "https://pokeapi.co/api/v2/move/590/"
      }
    ],
    "gen-omega-ruby-alpha-sapphire": [
      {
        "name": "flamethrower",
        "url": "https://pokeapi.co/api/v2/move/53/"
      },
      {
        "name": "hyper-beam",
        "url": "https://pokeapi.co/api/v2/move/63/"
      },
      {
        "name": "solar-beam",
        "url": "https://pokeapi.co/api/v2/move/76/"
      },
      {
        "name": "toxic",
        "url": "https://pokeapi.co/api/v2/move/92/"
      },
      {
        "name": "psychic",
        "url": "https://pokeapi.co/api/v2/move/94/"
      },
      {
        "name": "double-team",
        "url": "https://pokeapi.co/api/v2/move/104/"
      },
      {
        "name": "fire-blast",
        "url": "https://pokeapi.co/api/v2/move/126/"
      },
      {
        "name": "dream-eater",
        "url": "https://pokeapi.co/api/v2/move/138/"
      },
      {
        "name": "flash",
        "url": "https://pokeapi.co/api/v2/move/148/"
      },
      {
        "name": "rest",
        "url": "https://pokeapi.co/api/v2/move/156/"
      },
      {
        "name": "substitute",
        "url": "https://pokeapi.co/api/v2/move/164/"
      },
      {
        "name": "thief",
        "url": "https://pokeapi.co/api/v2/move/168/"
      },
      {
        "name": "protect",
        "url": "https://pokeapi.co/api/v2/move/182/"
      },
      {
        "name": "swagger",
        "url": "https://pokeapi.co/api/v2/move/207/"
      },
      {
        "name": "attract",
        "url": "https://pokeapi.co/api/v2/move/213/"
      },
      {
        "name": "sleep-talk",
        "url": "https://pokeapi.co/api/v2/move/214/"
      },
      {
        "name": "return",
        "url": "https://pokeapi.co/api/v2/move/216/"
      },
      {
        "name": "frustration",
        "url": "https://pokeapi.co/api/v2/move/218/"
      },
      {
        "name": "safeguard",
        "url": "https://pokeapi.co/api/v2/move/219/"
      },
      {
        "name": "hidden-power",
        "url": "https://pokeapi.co/api/v2/move/237/"
      },
      {
        "name": "sunny-day",
        "url": "https://pokeapi.co/api/v2/move/241/"
      },
      {
        "name": "psych-up",
        "url": "https://pokeapi.co/api/v2/move/244/"
      },
      {
        "name": "shadow-ball",
        "url": "https://pokeapi.co/api/v2/move/247/"
      },
      {
        "name": "will-o-wisp",
        "url": "https://pokeapi.co/api/v2/move/261/"
      },
      {
        "name": "facade",
        "url": "https://pokeapi.co/api/v2/move/263/"
      },
      {
        "name": "taunt",
        "url": "https://pokeapi.co/api/v2/move/269/"
      },
      {
        "name": "secret-power",
        "url": "https://pokeapi.co/api/v2/move/290/"
      },
      {
        "name": "overheat",
        "url": "https://pokeapi.co/api/v2/move/315/"
      },
      {
        "name": "calm-mind",
        "url": "https://pokeapi.co/api/v2/move/347/"
      },
      {
        "name": "payback",
        "url": "https://pokeapi.co/api/v2/move/371/"
      },
      {
        "name": "embargo",
        "url": "https://pokeapi.co/api/v2/move/373/"
      },
      {
        "name": "dark-pulse",
        "url": "https://pokeapi.co/api/v2/move/399/"
      },
      {
        "name": "energy-ball",
        "url": "https://pokeapi.co/api/v2/move/412/"
      },
      {
        "name": "giga-impact",
        "url": "https://pokeapi.co/api/v2/move/416/"
      },
      {
        "name": "trick-room",
        "url": "https://pokeapi.co/api/v2/move/433/"
      },
      {
        "name": "flame-charge",
        "url": "https://pokeapi.co/api/v2/move/488/"
      },
      {
        "name": "round",
        "url": "https://pokeapi.co/api/v2/move/496/"
      },
      {
        "name": "incinerate",
        "url": "https://pokeapi.co/api/v2/move/510/"
      },
      {
        "name": "confide",
        "url": "https://pokeapi.co/api/v2/move/590/"
      }
    ],
    "gen-sun-moon": [
      {
        "name": "flamethrower",
        "url": "https://pokeapi.co/api/v2/move/53/"
      },
      {
        "name": "hyper-beam",
        "url": "https://pokeapi.co/api/v2/move/63/"
      },
      {
        "name": "solar-beam",
        "url": "https://pokeapi.co/api/v2/move/76/"
      },
      {
        "name": "toxic",
        "url": "https://pokeapi.co/api/v2/move/92/"
      },
      {
        "name": "psychic",
        "url": "https://pokeapi.co/api/v2/move/94/"
      },
      {
        "name": "double-team",
        "url": "https://pokeapi.co/api/v2/move/104/"
      },
      {
        "name": "fire-blast",
        "url": "https://pokeapi.co/api/v2/move/126/"
      },
      {
        "name": "dream-eater",
        "url": "https://pokeapi.co/api/v2/move/138/"
      },
      {
        "name": "rest",
        "url": "https://pokeapi.co/api/v2/move/156/"
      },
      {
        "name": "substitute",
        "url": "https://pokeapi.co/api/v2/move/164/"
      },
      {
        "name": "thief",
        "url": "https://pokeapi.co/api/v2/move/168/"
      },
      {
        "name": "protect",
        "url": "https://pokeapi.co/api/v2/move/182/"
      },
      {
        "name": "swagger",
        "url": "https://pokeapi.co/api/v2/move/207/"
      },
      {
        "name": "attract",
        "url": "https://pokeapi.co/api/v2/move/213/"
      },
      {
        "name": "sleep-talk",
        "url": "https://pokeapi.co/api/v2/move/214/"
      },
      {
        "name": "return",
        "url": "https://pokeapi.co/api/v2/move/216/"
      },
      {
        "name": "frustration",
        "url": "https://pokeapi.co/api/v2/move/218/"
      },
      {
        "name": "safeguard",
        "url": "https://pokeapi.co/api/v2/move/219/"
      },
      {
        "name": "hidden-power",
        "url": "https://pokeapi.co/api/v2/move/237/"
      },
      {
        "name": "sunny-day",
        "url": "https://pokeapi.co/api/v2/move/241/"
      },
      {
        "name": "psych-up",
        "url": "https://pokeapi.co/api/v2/move/244/"
      },
      {
        "name": "shadow-ball",
        "url": "https://pokeapi.co/api/v2/move/247/"
      },
      {
        "name": "will-o-wisp",
        "url": "https://pokeapi.co/api/v2/move/261/"
      },
      {
        "name": "facade",
        "url": "https://pokeapi.co/api/v2/move/263/"
      },
      {
        "name": "taunt",
        "url": "https://pokeapi.co/api/v2/move/269/"
      },
      {
        "name": "overheat",
        "url": "https://pokeapi.co/api/v2/move/315/"
      },
      {
        "name": "calm-mind",
        "url": "https://pokeapi.co/api/v2/move/347/"
      },
      {
        "name": "payback",
        "url": "https://pokeapi.co/api/v2/move/371/"
      },
      {
        "name": "embargo",
        "url": "https://pokeapi.co/api/v2/move/373/"
      },
      {
        "name": "dark-pulse",
        "url": "https://pokeapi.co/api/v2/move/399/"
      },
      {
        "name": "energy-ball",
        "url": "https://pokeapi.co/api/v2/move/412/"
      },
      {
        "name": "giga-impact",
        "url": "https://pokeapi.co/api/v2/move/416/"
      },
      {
        "name": "trick-room",
        "url": "https://pokeapi.co/api/v2/move/433/"
      },
      {
        "name": "flame-charge",
        "url": "https://pokeapi.co/api/v2/move/488/"
      },
      {
        "name": "round",
        "url": "https://pokeapi.co/api/v2/move/496/"
      },
      {
        "name": "confide",
        "url": "https://pokeapi.co/api/v2/move/590/"
      }
    ],
    "gen-ultra-sun-ultra-moon": [
      {
        "name": "flamethrower",
        "url": "https://pokeapi.co/api/v2/move/53/"
      },
      {
        "name": "hyper-beam",
        "url": "https://pokeapi.co/api/v2/move/63/"
      },
      {
        "name": "solar-beam",
        "url": "https://pokeapi.co/api/v2/move/76/"
      },
      {
        "name": "toxic",
        "url": "https://pokeapi.co/api/v2/move/92/"
      },
      {
        "name": "psychic",
        "url": "https://pokeapi.co/api/v2/move/94/"
      },
      {
        "name": "double-team",
        "url": "https://pokeapi.co/api/v2/move/104/"
      },
      {
        "name": "fire-blast",
        "url": "https://pokeapi.co/api/v2/move/126/"
      },
      {
        "name": "dream-eater",
        "url": "https://pokeapi.co/api/v2/move/138/"
      },
      {
        "name": "rest",
        "url": "https://pokeapi.co/api/v2/move/156/"
      },
      {
        "name": "substitute",
        "url": "https://pokeapi.co/api/v2/move/164/"
      },
      {
        "name": "thief",
        "url": "https://pokeapi.co/api/v2/move/168/"
      },
      {
        "name": "protect",
        "url": "https://pokeapi.co/api/v2/move/182/"
      },
      {
        "name": "swagger",
        "url": "https://pokeapi.co/api/v2/move/207/"
      },
      {
        "name": "attract",
        "url": "https://pokeapi.co/api/v2/move/213/"
      },
      {
        "name": "sleep-talk",
        "url": "https://pokeapi.co/api/v2/move/214/"
      },
      {
        "name": "return",
        "url": "https://pokeapi.co/api/v2/move/216/"
      },
      {
        "name": "frustration",
        "url": "https://pokeapi.co/api/v2/move/218/"
      },
      {
        "name": "safeguard",
        "url": "https://pokeapi.co/api/v2/move/219/"
      },
      {
        "name": "hidden-power",
        "url": "https://pokeapi.co/api/v2/move/237/"
      },
      {
        "name": "sunny-day",
        "url": "https://pokeapi.co/api/v2/move/241/"
      },
      {
        "name": "psych-up",
        "url": "https://pokeapi.co/api/v2/move/244/"
      },
      {
        "name": "shadow-ball",
        "url": "https://pokeapi.co/api/v2/move/247/"
      },
      {
        "name": "will-o-wisp",
        "url": "https://pokeapi.co/api/v2/move/261/"
      },
      {
        "name": "facade",
        "url": "https://pokeapi.co/api/v2/move/263/"
      },
      {
        "name": "taunt",
        "url": "https://pokeapi.co/api/v2/move/269/"
      },
      {
        "name": "overheat",
        "url": "https://pokeapi.co/api/v2/move/315/"
      },
      {
        "name": "calm-mind",
        "url": "https://pokeapi.co/api/v2/move/347/"
      },
      {
        "name": "payback",
        "url": "https://pokeapi.co/api/v2/move/371/"
      },
      {
        "name": "embargo",
        "url": "https://pokeapi.co/api/v2/move/373/"
      },
      {
        "name": "dark-pulse",
        "url": "https://pokeapi.co/api/v2/move/399/"
      },
      {
        "name": "energy-ball",
        "url": "https://pokeapi.co/api/v2/move/412/"
      },
      {
        "name": "giga-impact",
        "url": "https://pokeapi.co/api/v2/move/416/"
      },
      {
        "name": "trick-room",
        "url": "https://pokeapi.co/api/v2/move/433/"
      },
      {
        "name": "flame-charge",
        "url": "https://pokeapi.co/api/v2/move/488/"
      },
      {
        "name": "round",
        "url": "https://pokeapi.co/api/v2/move/496/"
      },
      {
        "name": "confide",
        "url": "https://pokeapi.co/api/v2/move/590/"
      }
    ],
    "gen-sword-shield": [
      {
        "name": "flamethrower",
        "url": "https://pokeapi.co/api/v2/move/53/"
      },
      {
        "name": "hyper-beam",
        "url": "https://pokeapi.co/api/v2/move/63/"
      },
      {
        "name": "solar-beam",
        "url": "https://pokeapi.co/api/v2/move/76/"
      },
      {
        "name": "fire-spin",
        "url": "https://pokeapi.co/api/v2/move/83/"
      },
      {
        "name": "psychic",
        "url": "https://pokeapi.co/api/v2/move/94/"
      },
      {
        "name": "fire-blast",
        "url": "https://pokeapi.co/api/v2/move/126/"
      },
      {
        "name": "rest",
        "url": "https://pokeapi.co/api/v2/move/156/"
      },
      {
        "name": "substitute",
        "url": "https://pokeapi.co/api/v2/move/164/"
      },
      {
        "name": "thief",
        "url": "https://pokeapi.co/api/v2/move/168/"
      },
      {
        "name": "snore",
        "url": "https://pokeapi.co/api/v2/move/173/"
      },
      {
        "name": "protect",
        "url": "https://pokeapi.co/api/v2/move/182/"
      },
      {
        "name": "endure",
        "url": "https://pokeapi.co/api/v2/move/203/"
      },
      {
        "name": "attract",
        "url": "https://pokeapi.co/api/v2/move/213/"
      },
      {
        "name": "sleep-talk",
        "url": "https://pokeapi.co/api/v2/move/214/"
      },
      {
        "name": "safeguard",
        "url": "https://pokeapi.co/api/v2/move/219/"
      },
      {
        "name": "sunny-day",
        "url": "https://pokeapi.co/api/v2/move/241/"
      },
      {
        "name": "shadow-ball",
        "url": "https://pokeapi.co/api/v2/move/247/"
      },
      {
        "name": "heat-wave",
        "url": "https://pokeapi.co/api/v2/move/257/"
      },
      {
        "name": "will-o-wisp",
        "url": "https://pokeapi.co/api/v2/move/261/"
      },
      {
        "name": "facade",
        "url": "https://pokeapi.co/api/v2/move/263/"
      },
      {
        "name": "taunt",
        "url": "https://pokeapi.co/api/v2/move/269/"
      },
      {
        "name": "trick",
        "url": "https://pokeapi.co/api/v2/move/271/"
      },
      {
        "name": "imprison",
        "url": "https://pokeapi.co/api/v2/move/286/"
      },
      {
        "name": "overheat",
        "url": "https://pokeapi.co/api/v2/move/315/"
      },
      {
        "name": "calm-mind",
        "url": "https://pokeapi.co/api/v2/move/347/"
      },
      {
        "name": "payback",
        "url": "https://pokeapi.co/api/v2/move/371/"
      },
      {
        "name": "dark-pulse",
        "url": "https://pokeapi.co/api/v2/move/399/"
      },
      {
        "name": "energy-ball",
        "url": "https://pokeapi.co/api/v2/move/412/"
      },
      {
        "name": "giga-impact",
        "url": "https://pokeapi.co/api/v2/move/416/"
      },
      {
        "name": "trick-room",
        "url": "https://pokeapi.co/api/v2/move/433/"
      },
      {
        "name": "round",
        "url": "https://pokeapi.co/api/v2/move/496/"
      },
      {
        "name": "ally-switch",
        "url": "https://pokeapi.co/api/v2/move/502/"
      },
      {
        "name": "hex",
        "url": "https://pokeapi.co/api/v2/move/506/"
      },
      {
        "name": "mystical-fire",
        "url": "https://pokeapi.co/api/v2/move/595/"
      }
    ],
    "gen-scarlet-violet": [
      {
        "name": "flamethrower",
        "url": "https://pokeapi.co/api/v2/move/53/"
      },
      {
        "name": "hyper-beam",
        "url": "https://pokeapi.co/api/v2/move/63/"
      },
      {
        "name": "solar-beam",
        "url": "https://pokeapi.co/api/v2/move/76/"
      },
      {
        "name": "fire-spin",
        "url": "https://pokeapi.co/api/v2/move/83/"
      },
      {
        "name": "psychic",
        "url": "https://pokeapi.co/api/v2/move/94/"
      },
      {
        "name": "night-shade",
        "url": "https://pokeapi.co/api/v2/move/101/"
      },
      {
        "name": "confuse-ray",
        "url": "https://pokeapi.co/api/v2/move/109/"
      },
      {
        "name": "haze",
        "url": "https://pokeapi.co/api/v2/move/114/"
      },
      {
        "name": "fire-blast",
        "url": "https://pokeapi.co/api/v2/move/126/"
      },
      {
        "name": "rest",
        "url": "https://pokeapi.co/api/v2/move/156/"
      },
      {
        "name": "substitute",
        "url": "https://pokeapi.co/api/v2/move/164/"
      },
      {
        "name": "thief",
        "url": "https://pokeapi.co/api/v2/move/168/"
      },
      {
        "name": "curse",
        "url": "https://pokeapi.co/api/v2/move/174/"
      },
      {
        "name": "spite",
        "url": "https://pokeapi.co/api/v2/move/180/"
      },
      {
        "name": "protect",
        "url": "https://pokeapi.co/api/v2/move/182/"
      },
      {
        "name": "endure",
        "url": "https://pokeapi.co/api/v2/move/203/"
      },
      {
        "name": "sleep-talk",
        "url": "https://pokeapi.co/api/v2/move/214/"
      },
      {
        "name": "pain-split",
        "url": "https://pokeapi.co/api/v2/move/220/"
      },
      {
        "name": "sunny-day",
        "url": "https://pokeapi.co/api/v2/move/241/"
      },
      {
        "name": "psych-up",
        "url": "https://pokeapi.co/api/v2/move/244/"
      },
      {
        "name": "shadow-ball",
        "url": "https://pokeapi.co/api/v2/move/247/"
      },
      {
        "name": "heat-wave",
        "url": "https://pokeapi.co/api/v2/move/257/"
      },
      {
        "name": "will-o-wisp",
        "url": "https://pokeapi.co/api/v2/move/261/"
      },
      {
        "name": "facade",
        "url": "https://pokeapi.co/api/v2/move/263/"
      },
      {
        "name": "taunt",
        "url": "https://pokeapi.co/api/v2/move/269/"
      },
      {
        "name": "trick",
        "url": "https://pokeapi.co/api/v2/move/271/"
      },
      {
        "name": "imprison",
        "url": "https://pokeapi.co/api/v2/move/286/"
      },
      {
        "name": "overheat",
        "url": "https://pokeapi.co/api/v2/move/315/"
      },
      {
        "name": "calm-mind",
        "url": "https://pokeapi.co/api/v2/move/347/"
      },
      {
        "name": "flare-blitz",
        "url": "https://pokeapi.co/api/v2/move/394/"
      },
      {
        "name": "dark-pulse",
        "url": "https://pokeapi.co/api/v2/move/399/"
      },
      {
        "name": "energy-ball",
        "url": "https://pokeapi.co/api/v2/move/412/"
      },
      {
        "name": "giga-impact",
        "url": "https://pokeapi.co/api/v2/move/416/"
      },
      {
        "name": "trick-room",
        "url": "https://pokeapi.co/api/v2/move/433/"
      },
      {
        "name": "flame-charge",
        "url": "https://pokeapi.co/api/v2/move/488/"
      },
      {
        "name": "hex",
        "url": "https://pokeapi.co/api/v2/move/506/"
      },
      {
        "name": "skitter-smack",
        "url": "https://pokeapi.co/api/v2/move/806/"
      },
      {
        "name": "burning-jealousy",
        "url": "https://pokeapi.co/api/v2/move/807/"
      },
      {
        "name": "lash-out",
        "url": "https://pokeapi.co/api/v2/move/808/"
      },
      {
        "name": "poltergeist",
        "url": "https://pokeapi.co/api/v2/move/809/"
      },
      {
        "name": "tera-blast",
        "url": "https://pokeapi.co/api/v2/move/851/"
      },
      {
        "name": "trailblaze",
        "url": "https://pokeapi.co/api/v2/move/885/"
      },
      {
        "name": "temper-flare",
        "url": "https://pokeapi.co/api/v2/move/915/"
      }
    ]
  },
  "genus": "Luring Pokémon",
  "flavorText": "It absorbs a spirit, which it then burns.\nBy waving the flames on its arms,\nit puts its foes into a hypnotic trance."
}